setup.py
avrox/__init__.py
avrox/chat.py
avrox/people.py
avrox.egg-info/PKG-INFO
avrox.egg-info/SOURCES.txt
avrox.egg-info/dependency_links.txt
avrox.egg-info/top_level.txt