Metadata-Version: 2.1
Name: avrox
Version: 1.2.1
Summary:   有好玩的哦！    It's fun!
Home-page: https://github.com/avrox-github/
Author: avrox
Author-email: avrox163@163.com
License: UNKNOWN
Platform: UNKNOWN
Classifier: Programming Language :: Python :: 3
Classifier: License :: OSI Approved :: MIT License
Classifier: Operating System :: OS Independent
